aioaudiobookshelf/__init__.py
aioaudiobookshelf/exceptions.py
aioaudiobookshelf/helpers.py
aioaudiobookshelf/client/__init__.py
aioaudiobookshelf/client/_base.py
aioaudiobookshelf/client/authors.py
aioaudiobookshelf/client/collections_.py
aioaudiobookshelf/client/items.py
aioaudiobookshelf/client/libraries.py
aioaudiobookshelf/client/me.py
aioaudiobookshelf/client/playlists.py
aioaudiobookshelf/client/podcasts.py
aioaudiobookshelf/client/series.py
aioaudiobookshelf/client/session.py
aioaudiobookshelf/client/session_configuration.py
aioaudiobookshelf/schema/__init__.py
aioaudiobookshelf/schema/audio.py
aioaudiobookshelf/schema/author.py
aioaudiobookshelf/schema/book.py
aioaudiobookshelf/schema/calls_authors.py
aioaudiobookshelf/schema/calls_collections.py
aioaudiobookshelf/schema/calls_items.py
aioaudiobookshelf/schema/calls_library.py
aioaudiobookshelf/schema/calls_login.py
aioaudiobookshelf/schema/calls_me.py
aioaudiobookshelf/schema/calls_playlists.py
aioaudiobookshelf/schema/calls_series.py
aioaudiobookshelf/schema/calls_session.py
aioaudiobookshelf/schema/collection.py
aioaudiobookshelf/schema/events_socket.py
aioaudiobookshelf/schema/file.py
aioaudiobookshelf/schema/folder.py
aioaudiobookshelf/schema/library.py
aioaudiobookshelf/schema/media_progress.py
aioaudiobookshelf/schema/playlist.py
aioaudiobookshelf/schema/podcast.py
aioaudiobookshelf/schema/series.py
aioaudiobookshelf/schema/series_books.py
aioaudiobookshelf/schema/server.py
aioaudiobookshelf/schema/session.py
aioaudiobookshelf/schema/shelf.py
aioaudiobookshelf/schema/user.py
aioaudiobookshelf-0.1.8.dist-info/licenses/LICENSE
aioaudiobookshelf-0.1.8.dist-info/METADATA
aioaudiobookshelf-0.1.8.dist-info/WHEEL
aioaudiobookshelf-0.1.8.dist-info/top_level.txt
aioaudiobookshelf-0.1.8.dist-info/RECORD
